odoo/addons/hr_expense_sequence/README.rst
odoo/addons/hr_expense_sequence/__init__.py
odoo/addons/hr_expense_sequence/__manifest__.py
odoo/addons/hr_expense_sequence/hooks.py
odoo/addons/hr_expense_sequence/data/hr_expense_data.xml
odoo/addons/hr_expense_sequence/i18n/cs_CZ.po
odoo/addons/hr_expense_sequence/i18n/de.po
odoo/addons/hr_expense_sequence/i18n/es.po
odoo/addons/hr_expense_sequence/i18n/fi.po
odoo/addons/hr_expense_sequence/i18n/fr.po
odoo/addons/hr_expense_sequence/i18n/hr.po
odoo/addons/hr_expense_sequence/i18n/hr_expense_sequence.pot
odoo/addons/hr_expense_sequence/i18n/it.po
odoo/addons/hr_expense_sequence/i18n/nl_NL.po
odoo/addons/hr_expense_sequence/i18n/pt_BR.po
odoo/addons/hr_expense_sequence/i18n/sl.po
odoo/addons/hr_expense_sequence/models/__init__.py
odoo/addons/hr_expense_sequence/models/hr_expense_sheet.py
odoo/addons/hr_expense_sequence/readme/CONFIGURE.rst
odoo/addons/hr_expense_sequence/readme/CONTRIBUTORS.rst
odoo/addons/hr_expense_sequence/readme/DESCRIPTION.rst
odoo/addons/hr_expense_sequence/report/report_expense_sheet.xml
odoo/addons/hr_expense_sequence/static/description/icon.png
odoo/addons/hr_expense_sequence/static/description/index.html
odoo/addons/hr_expense_sequence/tests/__init__.py
odoo/addons/hr_expense_sequence/tests/test_hr_expense_sequence.py
odoo/addons/hr_expense_sequence/views/hr_expense_expense_view.xml
odoo14_addon_hr_expense_sequence-14.0.1.0.2.dist-info/METADATA
odoo14_addon_hr_expense_sequence-14.0.1.0.2.dist-info/WHEEL
odoo14_addon_hr_expense_sequence-14.0.1.0.2.dist-info/top_level.txt
odoo14_addon_hr_expense_sequence-14.0.1.0.2.dist-info/RECORD
